hw_runner/__init__.py
hw_runner/notebook_runner.py
hw_runner/runner.py
hw_runner-0.0.4.dist-info/LICENSE
hw_runner-0.0.4.dist-info/METADATA
hw_runner-0.0.4.dist-info/WHEEL
hw_runner-0.0.4.dist-info/top_level.txt
hw_runner-0.0.4.dist-info/RECORD
